integra_python_connect/__init__.py
integra_python_connect/adapters/__init__.py
integra_python_connect/adapters/ConnectorAdapter.py
integra_python_connect/adapters/ProcessorAdapter.py
integra_python_connect/api_router.py
integra_python_connect/bridge.py
integra_python_connect/common/__init__.py
integra_python_connect/common/dependency_manager.py
integra_python_connect/common/enums.py
integra_python_connect/common/settings.py
integra_python_connect/dto/__init__.py
integra_python_connect/dto/responces/__init__.py
integra_python_connect/dto/responces/external_service.py
integra_python_connect/dto/skeletons/__init__.py
integra_python_connect/dto/skeletons/connector.py
integra_python_connect/dto/skeletons/processor.py
integra_python_connect/dto/views/__init__.py
integra_python_connect/dto/views/connector_view.py
integra_python_connect/dto/views/processor_view.py
integra_python_connect/entity/__init__.py
integra_python_connect/entity/parametr.py
integra_python_connect/routers/__init__.py
integra_python_connect/routers/v1/__init__.py
integra_python_connect/routers/v1/base.py
integra_python_connect/routers/v1/configuration.py
integra_python_connect/routers/v1/processor.py
integra_python_connect/services/__init__.py
integra_python_connect/services/connector.py
integra_python_connect/services/external_service.py
integra_python_connect/services/processor.py
integra_python_connect-0.1.2.dist-info/METADATA
integra_python_connect-0.1.2.dist-info/WHEEL
integra_python_connect-0.1.2.dist-info/RECORD
