Metadata-Version: 2.1
Name: integra-python-connect
Version: 0.1.2
Summary: test discription
Author: Seventech
Requires-Python: >=3.12,<4.0
Classifier: Programming Language :: Python :: 3
Classifier: Programming Language :: Python :: 3.12
Requires-Dist: fastapi (>=0.111.0,<0.112.0)
Requires-Dist: pydantic-settings (>=2.3.1,<3.0.0)
